<HOP>
 <NAME>Hallertauer Mittelfrueh</NAME>
 <VERSION>1</VERSION>
 <ORIGIN>Germany</ORIGIN>
 <ALPHA>4.0000000</ALPHA>
 <AMOUNT>0.0000000</AMOUNT>
 <USE>Boil</USE>
 <TIME>0.0000000</TIME>
 <NOTES>Used for: Continental Lagers, German Ales/Lagers, US Lagers
Aroma: Pleasant, assertive, mild herbal aroma
Substitutes: Hallertauer, Mt. Hood, Liberty, Crystal
Examples: Sam Adams Boston Lager, Sam Adams Boston Lightship</NOTES>
 <TYPE>Aroma</TYPE>
 <FORM>Pellet</FORM>
 <BETA>4.6000000</BETA>
 <HSI>45.0000000</HSI>
 <DISPLAY_AMOUNT>0.00 oz</DISPLAY_AMOUNT>
 <INVENTORY>0.00 oz</INVENTORY>
 <DISPLAY_TIME>0.0 min</DISPLAY_TIME>
</HOP>